sm/__init__.py
sm/data/namespaces.yml
sm/dataset.py
sm/evaluation/__init__.py
sm/evaluation/cpa_cta_metrics.py
sm/evaluation/hierarchy_scoring_fn.py
sm/evaluation/precision_recall_f1.py
sm/evaluation/prelude.py
sm/evaluation/sm_metrics.py
sm/evaluation/transformation.py
sm/evaluation/utils.py
sm/inputs/__init__.py
sm/inputs/column.py
sm/inputs/context.py
sm/inputs/link.py
sm/inputs/prelude.py
sm/inputs/table.py
sm/misc/__init__.py
sm/misc/bijection.py
sm/misc/deser.py
sm/misc/exp_manager.py
sm/misc/fn_cache.py
sm/misc/funcs.py
sm/misc/logger.py
sm/misc/matrix.py
sm/misc/prelude.py
sm/misc/ray_helper.py
sm/misc/timer.py
sm/namespaces/__init__.py
sm/namespaces/dbpedia.py
sm/namespaces/namespace.py
sm/namespaces/prefix_index.py
sm/namespaces/prelude.py
sm/namespaces/utils.py
sm/namespaces/wikidata.py
sm/outputs/__init__.py
sm/outputs/_sm_formatter.py
sm/outputs/_sm_transform.py
sm/outputs/semantic_model.py
sm/prelude.py
sm/py.typed
sm/typing.py
sem_desc-6.19.3.dist-info/METADATA
sem_desc-6.19.3.dist-info/WHEEL
sem_desc-6.19.3.dist-info/RECORD
